{
  "lastUpdated": "2026-07-06T14:00:00+02:00",
  "note": "ESPN API provides live data. groupStage.playerStats used as fallback when ESPN unavailable.",
  "groupStage": {
    "goals": 148,
    "matches": 72,
    "yellowCards": 165,
    "redCards": 10,
    "penalties": 5,
    "note": "Group stage totals - used for tournament-wide calculations",
    "playerStats": {
      "Lionel Messi": { "country": "Argentina", "countryCode": "ARG", "flag": "AR", "club": "Inter Miami", "goals": 5, "assists": 1, "played": 3 },
      "Kylian Mbappé": { "country": "France", "countryCode": "FRA", "flag": "FR", "club": "Real Madrid", "goals": 4, "assists": 2, "played": 3 },
      "Erling Haaland": { "country": "Norway", "countryCode": "NOR", "flag": "NO", "club": "Man City", "goals": 3, "assists": 0, "played": 3 },
      "Harry Kane": { "country": "England", "countryCode": "ENG", "flag": "ENG", "club": "Bayern Munich", "goals": 4, "assists": 0, "played": 3 },
      "Ousmane Dembélé": { "country": "France", "countryCode": "FRA", "flag": "FR", "club": "PSG", "goals": 3, "assists": 1, "played": 3 },
      "Vinícius Júnior": { "country": "Brazil", "countryCode": "BRA", "flag": "BR", "club": "Real Madrid", "goals": 2, "assists": 1, "played": 3 },
      "Ismaïla Sarr": { "country": "Senegal", "countryCode": "SEN", "flag": "SN", "club": "Crystal Palace", "goals": 2, "assists": 0, "played": 3 },
      "Mikel Oyarzabal": { "country": "Spain", "countryCode": "ESP", "flag": "ES", "club": "Real Sociedad", "goals": 2, "assists": 1, "played": 3 },
      "Deniz Undav": { "country": "Germany", "countryCode": "GER", "flag": "DE", "club": "Stuttgart", "goals": 2, "assists": 2, "played": 3 },
      "Cristiano Ronaldo": { "country": "Portugal", "countryCode": "POR", "flag": "PT", "club": "Al Nassr", "goals": 2, "assists": 0, "played": 3 },
      "Julián Quiñones": { "country": "Mexico", "countryCode": "MEX", "flag": "MX", "club": "Club America", "goals": 2, "assists": 1, "played": 3 },
      "Cody Gakpo": { "country": "Netherlands", "countryCode": "NED", "flag": "NL", "club": "Liverpool", "goals": 2, "assists": 1, "played": 3 },
      "Folarin Balogun": { "country": "USA", "countryCode": "USA", "flag": "US", "club": "Monaco", "goals": 2, "assists": 0, "played": 3 },
      "Johan Manzambi": { "country": "Switzerland", "countryCode": "SUI", "flag": "CH", "club": "Young Boys", "goals": 2, "assists": 2, "played": 3 },
      "Jonathan David": { "country": "Canada", "countryCode": "CAN", "flag": "CA", "club": "Lille", "goals": 2, "assists": 0, "played": 3 },
      "Michael Olise": { "country": "France", "countryCode": "FRA", "flag": "FR", "club": "Bayern Munich", "goals": 1, "assists": 5, "played": 3 },
      "Bruno Guimarães": { "country": "Brazil", "countryCode": "BRA", "flag": "BR", "club": "Newcastle", "goals": 0, "assists": 4, "played": 3 },
      "Roberto Alvarado": { "country": "Mexico", "countryCode": "MEX", "flag": "MX", "club": "Chivas", "goals": 0, "assists": 3, "played": 3 },
      "Alexander Isak": { "country": "Sweden", "countryCode": "SWE", "flag": "SE", "club": "Newcastle", "goals": 2, "assists": 3, "played": 3 },
      "Martin Ødegaard": { "country": "Norway", "countryCode": "NOR", "flag": "NO", "club": "Arsenal", "goals": 1, "assists": 3, "played": 3 },
      "Florian Wirtz": { "country": "Germany", "countryCode": "GER", "flag": "DE", "club": "Leverkusen", "goals": 1, "assists": 3, "played": 3 },
      "Mohamed Salah": { "country": "Egypt", "countryCode": "EGY", "flag": "EG", "club": "Liverpool", "goals": 1, "assists": 2, "played": 3 },
      "Bukayo Saka": { "country": "England", "countryCode": "ENG", "flag": "ENG", "club": "Arsenal", "goals": 0, "assists": 2, "played": 3 },
      "Lamine Yamal": { "country": "Spain", "countryCode": "ESP", "flag": "ES", "club": "Barcelona", "goals": 0, "assists": 2, "played": 3 },
      "Romelu Lukaku": { "country": "Belgium", "countryCode": "BEL", "flag": "BE", "club": "Napoli", "goals": 2, "assists": 0, "played": 3 },
      "Kevin De Bruyne": { "country": "Belgium", "countryCode": "BEL", "flag": "BE", "club": "Man City", "goals": 1, "assists": 2, "played": 3 },
      "Julián Álvarez": { "country": "Argentina", "countryCode": "ARG", "flag": "AR", "club": "Atletico Madrid", "goals": 1, "assists": 1, "played": 3 },
      "Youssef En-Nesyri": { "country": "Morocco", "countryCode": "MAR", "flag": "MA", "club": "Sevilla", "goals": 2, "assists": 0, "played": 3 },
      "Hakim Ziyech": { "country": "Morocco", "countryCode": "MAR", "flag": "MA", "club": "Galatasaray", "goals": 1, "assists": 2, "played": 3 },
      "Achraf Hakimi": { "country": "Morocco", "countryCode": "MAR", "flag": "MA", "club": "PSG", "goals": 0, "assists": 1, "played": 3 },
      "Jude Bellingham": { "country": "England", "countryCode": "ENG", "flag": "ENG", "club": "Real Madrid", "goals": 2, "assists": 1, "played": 3 },
      "Raúl Jiménez": { "country": "Mexico", "countryCode": "MEX", "flag": "MX", "club": "Fulham", "goals": 2, "assists": 0, "played": 3 },
      "Rodrygo": { "country": "Brazil", "countryCode": "BRA", "flag": "BR", "club": "Real Madrid", "goals": 1, "assists": 1, "played": 3 },
      "Breel Embolo": { "country": "Switzerland", "countryCode": "SUI", "flag": "CH", "club": "Monaco", "goals": 1, "assists": 0, "played": 3 },
      "Miguel Almirón": { "country": "Paraguay", "countryCode": "PAR", "flag": "PY", "club": "Newcastle", "goals": 1, "assists": 1, "played": 3 },
      "Rafael Leão": { "country": "Portugal", "countryCode": "POR", "flag": "PT", "club": "AC Milan", "goals": 1, "assists": 1, "played": 3 },
      "Luis Díaz": { "country": "Colombia", "countryCode": "COL", "flag": "CO", "club": "Liverpool", "goals": 1, "assists": 1, "played": 3 },
      "Christian Pulisic": { "country": "USA", "countryCode": "USA", "flag": "US", "club": "AC Milan", "goals": 1, "assists": 1, "played": 3 },
      "Sébastien Haller": { "country": "Ivory Coast", "countryCode": "CIV", "flag": "CI", "club": "Borussia Dortmund", "goals": 1, "assists": 0, "played": 3 },
      "Takefusa Kubo": { "country": "Japan", "countryCode": "JPN", "flag": "JP", "club": "Real Sociedad", "goals": 1, "assists": 0, "played": 3 },
      "Luka Modrić": { "country": "Croatia", "countryCode": "CRO", "flag": "HR", "club": "Real Madrid", "goals": 1, "assists": 1, "played": 3 },
      "Santiago Giménez": { "country": "Mexico", "countryCode": "MEX", "flag": "MX", "club": "Feyenoord", "goals": 1, "assists": 0, "played": 3 },
      "Cédric Bakambu": { "country": "DR Congo", "countryCode": "COD", "flag": "CD", "club": "Galatasaray", "goals": 1, "assists": 0, "played": 3 },
      "Mitchell Duke": { "country": "Australia", "countryCode": "AUS", "flag": "AU", "club": "Machida Zelvia", "goals": 1, "assists": 0, "played": 3 },
      "Garry Rodrigues": { "country": "Cape Verde", "countryCode": "CPV", "flag": "CV", "club": "Al-Ittihad", "goals": 1, "assists": 0, "played": 3 },
      "Ryan Mendes": { "country": "Cape Verde", "countryCode": "CPV", "flag": "CV", "club": "Guimarães", "goals": 1, "assists": 0, "played": 3 }
    },
    "teamGoals": {
      "France": 12,
      "Spain": 10,
      "Argentina": 9,
      "Germany": 9,
      "Brazil": 8,
      "England": 8,
      "Portugal": 8,
      "Belgium": 7,
      "Morocco": 7,
      "Mexico": 7,
      "USA": 6,
      "Netherlands": 6,
      "Norway": 6,
      "Colombia": 5,
      "Switzerland": 5
    },
    "teamYellowCards": {
      "Haiti": 7,
      "Bosnia": 6,
      "Paraguay": 4,
      "Brazil": 4,
      "Canada": 4,
      "Scotland": 5,
      "Argentina": 4,
      "Germany": 4,
      "Mexico": 3,
      "Morocco": 3,
      "France": 3,
      "USA": 3,
      "England": 3,
      "Spain": 2,
      "Portugal": 3,
      "Belgium": 3,
      "Netherlands": 3,
      "Norway": 2,
      "Switzerland": 2,
      "Colombia": 3,
      "Egypt": 3,
      "Senegal": 4,
      "Sweden": 3,
      "Japan": 2,
      "Ivory Coast": 3,
      "Ecuador": 3,
      "DR Congo": 3,
      "Croatia": 3,
      "Austria": 2,
      "Algeria": 3,
      "Australia": 3,
      "Cape Verde": 2,
      "Ghana": 2,
      "South Africa": 4
    }
  },
  "careerWCGoals": {
    "Messi": { "pre2026": 13, "note": "Goals before 2026 WC (2006-2022)" },
    "Ronaldo": { "pre2026": 9, "note": "Goals before 2026 WC (2006-2022)" },
    "Klose": { "total": 16, "note": "All-time record holder (2002-2014)" }
  },
  "goldenBoot": [],
  "assists": [],
  "dataSource": {
    "goldenBoot": "ESPN API (primary) or groupStage.playerStats + matches.json scorers (fallback)",
    "assists": "ESPN API (primary) or groupStage.playerStats + matches.json scorers (fallback)",
    "yellowCards": "Calculated from groupStage.teamYellowCards + matches.json discipline",
    "redCards": "Calculated from groupStage.redCards + matches.json discipline",
    "refereeStats": "Calculated from matches.json referee assignments",
    "penalties": "Calculated from groupStage.penalties + matches.json discipline"
  }
}
